{"$schema":"http://sheets.flechs.net/MTFON.json","name":"Cauldron-Born","model":"Prime","version":"1.0","config":"Biped Omnimech","techbase":"Clan","era":"3049","source":"TRO 3058 - Clan Invasion","rules level":"2","mass":"65","engine":"325 XL (Clan) Engine","structure":"Endo Steel","myomer":"Standard","heat sinks":"13 Double","base chassis heat sinks":"13","walk mp":"5","jump mp":"0","armor":"Ferro-Fibrous(Clan)","la armor":"17","ra armor":"17","lt armor":"22","rt armor":"22","ct armor":"32","hd armor":"9","ll armor":"19","rl armor":"19","rtl armor":"8","rtr armor":"8","rtc armor":"9","weapons":[{"count":1,"mtfName":"ER Medium Laser","location":"Left Torso"},{"count":1,"mtfName":"LRM 10","location":"Left Torso"},{"count":1,"mtfName":"SRM 2","location":"Right Torso"},{"count":1,"mtfName":"Gauss Rifle","location":"Right Arm"},{"count":1,"mtfName":"LB 5-X AC","location":"Left Arm"}],"left arm":["Shoulder","Upper Arm Actuator","CLLBXAC5","CLLBXAC5","CLLBXAC5","CLLBXAC5","Clan LB 5-X AC Ammo","Clan LB 5-X Cluster Ammo","Ferro-Fibrous","Ferro-Fibrous","-Empty-","-Empty-"],"right arm":["Shoulder","Upper Arm Actuator","CLGaussRifle","CLGaussRifle","CLGaussRifle","CLGaussRifle","CLGaussRifle","CLGaussRifle","Ferro-Fibrous","Ferro-Fibrous","-Empty-","-Empty-"],"left torso":["Fusion Engine","Fusion Engine","CLLRM10","CLERMediumLaser","Clan Ammo LRM-10","Clan Ammo LRM-10","Endo Steel","Ferro-Fibrous","-Empty-","-Empty-","-Empty-","-Empty-"],"right torso":["Fusion Engine","Fusion Engine","CLSRM2","Clan Ammo SRM-2","Clan Gauss Ammo","Clan Gauss Ammo","Endo Steel","-Empty-","-Empty-","-Empty-","-Empty-","-Empty-"],"center torso":["Fusion Engine","Fusion Engine","Fusion Engine","Gyro","Gyro","Gyro","Gyro","Fusion Engine","Fusion Engine","Fusion Engine","Endo Steel","Ferro-Fibrous"],"head":["Life Support","Sensors","Cockpit","Ferro-Fibrous","Sensors","Life Support","-Empty-","-Empty-","-Empty-","-Empty-","-Empty-","-Empty-"],"left leg":["Hip","Upper Leg Actuator","Lower Leg Actuator","Foot Actuator","Endo Steel","Endo Steel","-Empty-","-Empty-","-Empty-","-Empty-","-Empty-","-Empty-"],"right leg":["Hip","Upper Leg Actuator","Lower Leg Actuator","Foot Actuator","Endo Steel","Endo Steel","-Empty-","-Empty-","-Empty-","-Empty-","-Empty-","-Empty-"],"alias":"Ebon Jaguar","designation":"Cauldron-Born Prime","validMTF":true}