{"$schema":"http://sheets.flechs.net/MTFON.json","name":"Centurion","model":"CN9-Ar","version":"1.0","config":"Biped","techbase":"Inner Sphere","era":"3072","source":"Jihad","rules level":"2","mass":"50","engine":"200 Fusion Engine(IS)","structure":"Standard","myomer":"Standard","heat sinks":"10 Double","walk mp":"4","jump mp":"0","armor":"Standard(Inner Sphere)","la armor":"16","ra armor":"16","lt armor":"13","rt armor":"13","ct armor":"18","hd armor":"9","ll armor":"16","rl armor":"16","rtl armor":"6","rtr armor":"6","rtc armor":"7","weapons":[{"count":1,"mtfName":"Heavy PPC","location":"Right Arm"},{"count":1,"mtfName":"Light PPC","location":"Right Arm"},{"count":1,"mtfName":"LRM 10","location":"Left Torso"},{"count":1,"mtfName":"Medium Laser","location":"Center Torso"},{"count":1,"mtfName":"Medium Pulse Laser","location":"Center Torso"}],"left arm":["Shoulder","Upper Arm Actuator","Lower Arm Actuator","Hand Actuator","-Empty-","-Empty-","-Empty-","-Empty-","-Empty-","-Empty-","-Empty-","-Empty-"],"right arm":["Shoulder","Upper Arm Actuator","Lower Arm Actuator","Heavy PPC","Heavy PPC","Heavy PPC","Heavy PPC","Light PPC","Light PPC","-Empty-","-Empty-","-Empty-"],"left torso":["ISDoubleHeatSink","ISDoubleHeatSink","ISDoubleHeatSink","LRM 10","LRM 10","IS Ammo LRM-10","IS Ammo LRM-10","-Empty-","-Empty-","-Empty-","-Empty-","-Empty-"],"right torso":["ISDoubleHeatSink","ISDoubleHeatSink","ISDoubleHeatSink","-Empty-","-Empty-","-Empty-","-Empty-","-Empty-","-Empty-","-Empty-","-Empty-","-Empty-"],"center torso":["Fusion Engine","Fusion Engine","Fusion Engine","Gyro","Gyro","Gyro","Gyro","Fusion Engine","Fusion Engine","Fusion Engine","Medium Laser","ISMediumPulseLaser (R)"],"head":["Life Support","Sensors","Cockpit","-Empty-","Sensors","Life Support","-Empty-","-Empty-","-Empty-","-Empty-","-Empty-","-Empty-"],"left leg":["Hip","Upper Leg Actuator","Lower Leg Actuator","Foot Actuator","-Empty-","-Empty-","-Empty-","-Empty-","-Empty-","-Empty-","-Empty-","-Empty-"],"right leg":["Hip","Upper Leg Actuator","Lower Leg Actuator","Foot Actuator","-Empty-","-Empty-","-Empty-","-Empty-","-Empty-","-Empty-","-Empty-","-Empty-"],"imagefile":".\\data\\images\\fluff\\Mech\\3039Centurion.jpg","designation":"Centurion CN9-Ar","validMTF":true}