{"$schema":"http://sheets.flechs.net/MTFON.json","name":"Longshot","model":"LNG-2","version":"1.0","config":"Biped","techbase":"Inner Sphere","era":"3058","source":"TRO 3055 - Clan Invasion","rules level":"4","mass":"35","engine":"245 XL Engine","structure":"Endo Steel","myomer":"Standard","heat sinks":"10 Double","walk mp":"7","jump mp":"0","armor":"Reactive(Inner Sphere)","la armor":"7","ra armor":"7","lt armor":"11","rt armor":"11","ct armor":"14","hd armor":"9","ll armor":"10","rl armor":"10","rtl armor":"5","rtr armor":"5","rtc armor":"7","weapons":[{"count":1,"mtfName":"SRM 6","location":"Left Torso"},{"count":1,"mtfName":"Medium X-Pulse Laser","location":"Left Torso"},{"count":1,"mtfName":"Small X-Pulse Laser","location":"Left Torso"},{"count":1,"mtfName":"SRM 6","location":"Right Torso"},{"count":1,"mtfName":"Medium X-Pulse Laser","location":"Right Torso"},{"count":1,"mtfName":"Small X-Pulse Laser","location":"Right Torso"}],"left arm":["Shoulder","Upper Arm Actuator","Lower Arm Actuator","Hand Actuator","ISDoubleHeatSink","ISDoubleHeatSink","ISDoubleHeatSink","Reactive","Reactive","Reactive","Reactive","Reactive"],"right arm":["Shoulder","Upper Arm Actuator","Lower Arm Actuator","Endo Steel","Endo Steel","Endo Steel","Endo Steel","Reactive","Reactive","Reactive","Reactive","Reactive"],"left torso":["Fusion Engine","Fusion Engine","Fusion Engine","SRM 6","SRM 6","ISArtemisIV","ISMediumXPulseLaser","ISSmallXPulseLaser","Endo Steel","Endo Steel","Reactive","Reactive"],"right torso":["Fusion Engine","Fusion Engine","Fusion Engine","SRM 6","SRM 6","ISArtemisIV","ISMediumXPulseLaser","ISSmallXPulseLaser","IS Ammo SRM-6 Artemis-capable","Endo Steel","Reactive","Reactive"],"center torso":["Fusion Engine","Fusion Engine","Fusion Engine","Gyro","Gyro","Gyro","Gyro","Fusion Engine","Fusion Engine","Fusion Engine","Endo Steel","Endo Steel"],"head":["Life Support","Sensors","Cockpit","Endo Steel","Sensors","Life Support","-Empty-","-Empty-","-Empty-","-Empty-","-Empty-","-Empty-"],"left leg":["Hip","Upper Leg Actuator","Lower Leg Actuator","Foot Actuator","Endo Steel","Endo Steel","-Empty-","-Empty-","-Empty-","-Empty-","-Empty-","-Empty-"],"right leg":["Hip","Upper Leg Actuator","Lower Leg Actuator","Foot Actuator","Endo Steel","Endo Steel","-Empty-","-Empty-","-Empty-","-Empty-","-Empty-","-Empty-"],"designation":"Longshot LNG-2","validMTF":true}