{"$schema":"http://sheets.flechs.net/MTFON.json","name":"Mad Cat III","model":"Eve","version":"1.0","config":"Biped","techbase":"Clan","era":"3086","source":"DTP Liao","rules level":"2","mass":"55","engine":"330 XL (Clan) Engine(IS)","structure":"Endo Steel","myomer":"Standard","heat sinks":"14 Double","walk mp":"6","jump mp":"0","armor":"Ferro-Fibrous(Clan)","la armor":"15","ra armor":"15","lt armor":"21","rt armor":"21","ct armor":"28","hd armor":"9","ll armor":"20","rl armor":"20","rtl armor":"4","rtr armor":"4","rtc armor":"6","weapons":[{"count":1,"mtfName":"ER Medium Laser","location":"Left Arm"},{"count":1,"mtfName":"ER Medium Laser","location":"Left Arm"},{"count":1,"mtfName":"ER PPC","location":"Right Arm"},{"count":1,"mtfName":"LRM 10","location":"Left Torso"},{"count":1,"mtfName":"LRM 10","location":"Right Torso"},{"count":1,"mtfName":"Clan TAG","location":"Center Torso"}],"left arm":["Shoulder","Upper Arm Actuator","Lower Arm Actuator","CLERMediumLaser","CLERMediumLaser","Endo Steel","Endo Steel","Ferro-Fibrous","Ferro-Fibrous","-Empty-","-Empty-","-Empty-"],"right arm":["Shoulder","Upper Arm Actuator","Lower Arm Actuator","CLERPPC","CLERPPC","Endo Steel","Endo Steel","Ferro-Fibrous","Ferro-Fibrous","-Empty-","-Empty-","-Empty-"],"left torso":["Fusion Engine","Fusion Engine","CLLRM10","CLArtemisIV","Clan Ammo LRM-10 (Clan) Artemis-capable","Endo Steel","Endo Steel","Ferro-Fibrous","-Empty-","-Empty-","-Empty-","-Empty-"],"right torso":["Fusion Engine","Fusion Engine","CLLRM10","CLArtemisIV","Clan Ammo LRM-10 (Clan) Artemis-capable","CLTargeting Computer","CLTargeting Computer","Endo Steel","Ferro-Fibrous","-Empty-","-Empty-","-Empty-"],"center torso":["Fusion Engine","Fusion Engine","Fusion Engine","Gyro","Gyro","Gyro","Gyro","Fusion Engine","Fusion Engine","Fusion Engine","CLTAG","Ferro-Fibrous"],"head":["Life Support","Sensors","Cockpit","-Empty-","Sensors","Life Support","-Empty-","-Empty-","-Empty-","-Empty-","-Empty-","-Empty-"],"left leg":["Hip","Upper Leg Actuator","Lower Leg Actuator","Foot Actuator","-Empty-","-Empty-","-Empty-","-Empty-","-Empty-","-Empty-","-Empty-","-Empty-"],"right leg":["Hip","Upper Leg Actuator","Lower Leg Actuator","Foot Actuator","CLDoubleHeatSink","CLDoubleHeatSink","-Empty-","-Empty-","-Empty-","-Empty-","-Empty-","-Empty-"],"designation":"Mad Cat III Eve","validMTF":true}