{"$schema":"http://sheets.flechs.net/MTFON.json","name":"Ryoken II","model":"Standard","version":"1.0","config":"Biped","techbase":"Clan","era":"3075","source":"TRO 3075","rules level":"2","mass":"75","engine":"375 XL (Clan) Engine","structure":"Endo Steel","myomer":"Standard","heat sinks":"10 Double","walk mp":"5","jump mp":"0","armor":"Standard(Clan)","la armor":"22","ra armor":"22","lt armor":"22","rt armor":"22","ct armor":"32","hd armor":"9","ll armor":"30","rl armor":"30","rtl armor":"8","rtr armor":"8","rtc armor":"11","weapons":[{"count":1,"mtfName":"LRM 15","location":"Left Torso"},{"count":1,"mtfName":"LRM 15","location":"Right Torso"},{"count":1,"mtfName":"LB 2-X AC","location":"Left Torso"},{"count":1,"mtfName":"LB 2-X AC","location":"Left Torso"},{"count":1,"mtfName":"LB 2-X AC","location":"Right Torso"},{"count":1,"mtfName":"LB 2-X AC","location":"Right Torso"}],"left arm":["Shoulder","Upper Arm Actuator","Lower Arm Actuator","Hand Actuator","-Empty-","-Empty-","-Empty-","-Empty-","-Empty-","-Empty-","-Empty-","-Empty-"],"right arm":["Shoulder","Upper Arm Actuator","Lower Arm Actuator","Hand Actuator","-Empty-","-Empty-","-Empty-","-Empty-","-Empty-","-Empty-","-Empty-","-Empty-"],"left torso":["Fusion Engine","Fusion Engine","CLLRM15","CLLRM15","CLLBXAC2","CLLBXAC2","CLLBXAC2","CLLBXAC2","CLLBXAC2","CLLBXAC2","Clan Ammo LRM-15","Clan LB 2-X AC Ammo"],"right torso":["Fusion Engine","Fusion Engine","CLLRM15","CLLRM15","CLLBXAC2","CLLBXAC2","CLLBXAC2","CLLBXAC2","CLLBXAC2","CLLBXAC2","Clan Ammo LRM-15","Clan LB 2-X Cluster Ammo"],"center torso":["Fusion Engine","Fusion Engine","Fusion Engine","Gyro","Gyro","Gyro","Gyro","Fusion Engine","Fusion Engine","Fusion Engine","Endo Steel","Endo Steel"],"head":["Life Support","Sensors","Cockpit","Endo Steel","Sensors","Life Support","-Empty-","-Empty-","-Empty-","-Empty-","-Empty-","-Empty-"],"left leg":["Hip","Upper Leg Actuator","Lower Leg Actuator","Foot Actuator","Endo Steel","Endo Steel","-Empty-","-Empty-","-Empty-","-Empty-","-Empty-","-Empty-"],"right leg":["Hip","Upper Leg Actuator","Lower Leg Actuator","Foot Actuator","Endo Steel","Endo Steel","-Empty-","-Empty-","-Empty-","-Empty-","-Empty-","-Empty-"],"designation":"Ryoken II Standard","validMTF":true}