{"$schema":"http://sheets.flechs.net/MTFON.json","name":"Sasquatch","model":"SQS-TH-001","version":"1.0","config":"Biped","techbase":"Inner Sphere","era":"3054","source":"TRO 3055 - Clan Invasion","rules level":"2","mass":"85","engine":"340 XL Engine","structure":"Standard","myomer":"Standard","heat sinks":"14 Double","walk mp":"4","jump mp":"4","armor":"Standard(Inner Sphere)","la armor":"26","ra armor":"26","lt armor":"27","rt armor":"27","ct armor":"39","hd armor":"9","ll armor":"33","rl armor":"33","rtl armor":"8","rtr armor":"8","rtc armor":"12","weapons":[{"count":1,"mtfName":"Medium Pulse Laser","location":"Left Arm"},{"count":1,"mtfName":"Medium Pulse Laser","location":"Left Arm"},{"count":1,"mtfName":"Medium Pulse Laser","location":"Left Arm"},{"count":1,"mtfName":"Medium Pulse Laser","location":"Left Arm"},{"count":1,"mtfName":"Gauss Rifle","location":"Right Arm"},{"count":1,"mtfName":"Machine Gun","location":"Left Torso"},{"count":1,"mtfName":"SRM 6","location":"Right Torso"},{"count":1,"mtfName":"Machine Gun","location":"Right Torso"},{"count":1,"mtfName":"AMS","location":"Right Torso"},{"count":1,"mtfName":"Small Laser","location":"Head"}],"left arm":["Shoulder","Upper Arm Actuator","Lower Arm Actuator","Hand Actuator","ISMediumPulseLaser","ISMediumPulseLaser","ISMediumPulseLaser","ISMediumPulseLaser","-Empty-","-Empty-","-Empty-","-Empty-"],"right arm":["Shoulder","Upper Arm Actuator","Lower Arm Actuator","ISGaussRifle","ISGaussRifle","ISGaussRifle","ISGaussRifle","ISGaussRifle","ISGaussRifle","ISGaussRifle","IS Gauss Ammo","IS Gauss Ammo"],"left torso":["Fusion Engine","Fusion Engine","Fusion Engine","ISDoubleHeatSink","ISDoubleHeatSink","ISDoubleHeatSink","Machine Gun","-Empty-","-Empty-","-Empty-","-Empty-","-Empty-"],"right torso":["Fusion Engine","Fusion Engine","Fusion Engine","SRM 6","SRM 6","Machine Gun","ISAntiMissileSystem","IS Machine Gun Ammo - Half","IS Ammo SRM-6","ISAMS Ammo","-Empty-","-Empty-"],"center torso":["Fusion Engine","Fusion Engine","Fusion Engine","Gyro","Gyro","Gyro","Gyro","Fusion Engine","Fusion Engine","Fusion Engine","-Empty-","-Empty-"],"head":["Life Support","Sensors","Cockpit","Small Laser (R)","Sensors","Life Support","-Empty-","-Empty-","-Empty-","-Empty-","-Empty-","-Empty-"],"left leg":["Hip","Upper Leg Actuator","Lower Leg Actuator","Foot Actuator","Jump Jet","Jump Jet","-Empty-","-Empty-","-Empty-","-Empty-","-Empty-","-Empty-"],"right leg":["Hip","Upper Leg Actuator","Lower Leg Actuator","Foot Actuator","Jump Jet","Jump Jet","-Empty-","-Empty-","-Empty-","-Empty-","-Empty-","-Empty-"],"designation":"Sasquatch SQS-TH-001","validMTF":true}