{"$schema":"http://sheets.flechs.net/MTFON.json","name":"Sunder","model":"SD1-OC","version":"1.0","config":"Biped Omnimech","techbase":"Inner Sphere","era":"3058","source":"TRO 3058 - Clan Invasion","rules level":"2","mass":"90","engine":"360 XL Engine","structure":"Standard","myomer":"Standard","heat sinks":"15 Double","base chassis heat sinks":"14","walk mp":"4","jump mp":"0","armor":"Standard(Inner Sphere)","la armor":"30","ra armor":"30","lt armor":"28","rt armor":"28","ct armor":"41","hd armor":"9","ll armor":"33","rl armor":"33","rtl armor":"10","rtr armor":"10","rtc armor":"12","weapons":[{"count":1,"mtfName":"MRM 40","location":"Left Arm"},{"count":1,"mtfName":"MRM 30","location":"Right Arm"},{"count":1,"mtfName":"Medium Laser","location":"Left Torso"},{"count":1,"mtfName":"Streak SRM 4","location":"Center Torso"},{"count":1,"mtfName":"Streak SRM 4","location":"Head"}],"left arm":["Shoulder","Upper Arm Actuator","MRM 40","MRM 40","MRM 40","MRM 40","MRM 40","MRM 40","MRM 40","IS MRM 40 Ammo","IS MRM 40 Ammo","IS MRM 40 Ammo"],"right arm":["Shoulder","Upper Arm Actuator","Lower Arm Actuator","ISDoubleHeatSink","ISDoubleHeatSink","ISDoubleHeatSink","MRM 30","MRM 30","MRM 30","MRM 30","MRM 30","-Empty-"],"left torso":["Fusion Engine","Fusion Engine","Fusion Engine","Medium Laser","ISC3SlaveUnit","-Empty-","-Empty-","-Empty-","-Empty-","-Empty-","-Empty-","-Empty-"],"right torso":["Fusion Engine","Fusion Engine","Fusion Engine","IS MRM 30 Ammo","IS MRM 30 Ammo","-Empty-","-Empty-","-Empty-","-Empty-","-Empty-","-Empty-","-Empty-"],"center torso":["Fusion Engine","Fusion Engine","Fusion Engine","Gyro","Gyro","Gyro","Gyro","Fusion Engine","Fusion Engine","Fusion Engine","ISStreakSRM4","IS Streak SRM 4 Ammo"],"head":["Life Support","Sensors","Cockpit","ISStreakSRM4","Sensors","Life Support","-Empty-","-Empty-","-Empty-","-Empty-","-Empty-","-Empty-"],"left leg":["Hip","Upper Leg Actuator","Lower Leg Actuator","Foot Actuator","-Empty-","-Empty-","-Empty-","-Empty-","-Empty-","-Empty-","-Empty-","-Empty-"],"right leg":["Hip","Upper Leg Actuator","Lower Leg Actuator","Foot Actuator","-Empty-","-Empty-","-Empty-","-Empty-","-Empty-","-Empty-","-Empty-","-Empty-"],"designation":"Sunder SD1-OC","validMTF":true}