{"$schema":"http://sheets.flechs.net/MTFON.json","name":"Valkyrie","model":"VLK-QD2","version":"1.2","config":"Biped","techbase":"Inner Sphere","era":"3072","source":"Jihad","rules level":"2","mass":"30","engine":"150 XL Engine","structure":"Endo Steel","myomer":"Standard","ejection":"Full Head Ejection System","heat sinks":"10 Double","walk mp":"5","jump mp":"5","armor":"Standard(Inner Sphere)","la armor":"8","ra armor":"8","lt armor":"8","rt armor":"8","ct armor":"9","hd armor":"8","ll armor":"11","rl armor":"11","rtl armor":"3","rtr armor":"3","rtc armor":"3","weapons":[{"count":1,"mtfName":"ER Medium Laser","location":"Right Arm"},{"count":1,"mtfName":"Light Auto Cannon/2","location":"Left Torso"},{"count":1,"mtfName":"Light Auto Cannon/2","location":"Left Torso"}],"left arm":["Shoulder","Upper Arm Actuator","Lower Arm Actuator","Hand Actuator","Endo Steel","Endo Steel","Endo Steel","Endo Steel","Endo Steel","Endo Steel","Endo Steel","-Empty-"],"right arm":["Shoulder","Upper Arm Actuator","Lower Arm Actuator","ISERMediumLaser","Endo Steel","Endo Steel","Endo Steel","Endo Steel","Endo Steel","Endo Steel","Endo Steel","-Empty-"],"left torso":["Fusion Engine","Fusion Engine","Fusion Engine","ISDoubleHeatSink","ISDoubleHeatSink","ISDoubleHeatSink","Light Auto Cannon/2","Light Auto Cannon/2","IS Ammo LAC/2","ISTargeting Computer","ISTargeting Computer","ISTargeting Computer"],"right torso":["Fusion Engine","Fusion Engine","Fusion Engine","ISDoubleHeatSink","ISDoubleHeatSink","ISDoubleHeatSink","ISDoubleHeatSink","ISDoubleHeatSink","ISDoubleHeatSink","ISDoubleHeatSink","ISDoubleHeatSink","ISDoubleHeatSink"],"center torso":["Fusion Engine","Fusion Engine","Fusion Engine","Gyro","Gyro","Gyro","Gyro","Fusion Engine","Fusion Engine","Fusion Engine","Jump Jet","-Empty-"],"head":["Life Support","Sensors","Cockpit","-Empty-","Sensors","Life Support","-Empty-","-Empty-","-Empty-","-Empty-","-Empty-","-Empty-"],"left leg":["Hip","Upper Leg Actuator","Lower Leg Actuator","Foot Actuator","Jump Jet","Jump Jet","-Empty-","-Empty-","-Empty-","-Empty-","-Empty-","-Empty-"],"right leg":["Hip","Upper Leg Actuator","Lower Leg Actuator","Foot Actuator","Jump Jet","Jump Jet","-Empty-","-Empty-","-Empty-","-Empty-","-Empty-","-Empty-"],"designation":"Valkyrie VLK-QD2","validMTF":true}