{"$schema":"http://sheets.flechs.net/MTFON.json","name":"Xanthos","model":"XNT-3O","version":"1.0","config":"Quad","techbase":"Inner Sphere","era":"2579","source":"TRO 3075","rules level":"2","mass":"100","engine":"300 Fusion Engine","structure":"Standard","myomer":"Standard","heat sinks":"23 Single","walk mp":"3","jump mp":"0","armor":"Standard(Inner Sphere)","fll armor":"42","frl armor":"42","lt armor":"32","rt armor":"32","ct armor":"46","hd armor":"9","rll armor":"42","rrl armor":"42","rtl armor":"10","rtr armor":"10","rtc armor":"16","weapons":[{"count":1,"mtfName":"Particle Cannon","location":"Left Torso"},{"count":1,"mtfName":"SRM 6","location":"Left Torso"},{"count":1,"mtfName":"Medium Laser","location":"Left Torso"},{"count":1,"mtfName":"Small Laser","location":"Left Torso"},{"count":1,"mtfName":"Autocannon/20","location":"Right Torso"},{"count":1,"mtfName":"Medium Laser","location":"Right Torso"},{"count":1,"mtfName":"Medium Laser","location":"Head"}],"front left leg":["Hip","Upper Leg Actuator","Lower Leg Actuator","Foot Actuator","Heat Sink","Heat Sink","-Empty-","-Empty-","-Empty-","-Empty-","-Empty-","-Empty-"],"front right leg":["Hip","Upper Leg Actuator","Lower Leg Actuator","Foot Actuator","Heat Sink","-Empty-","-Empty-","-Empty-","-Empty-","-Empty-","-Empty-","-Empty-"],"left torso":["Heat Sink","Heat Sink","Particle Cannon","Particle Cannon","Particle Cannon","SRM 6","SRM 6","Medium Laser","Small Laser (R)","IS Ammo SRM-6","IS Ammo AC/20","IS Ammo AC/20"],"right torso":["Autocannon/20","Autocannon/20","Autocannon/20","Autocannon/20","Autocannon/20","Autocannon/20","Autocannon/20","Autocannon/20","Autocannon/20","Autocannon/20","Medium Laser","IS Ammo AC/20"],"center torso":["Fusion Engine","Fusion Engine","Fusion Engine","Gyro","Gyro","Gyro","Gyro","Fusion Engine","Fusion Engine","Fusion Engine","Heat Sink","Heat Sink"],"head":["Life Support","Sensors","Cockpit","Medium Laser","Sensors","Life Support","-Empty-","-Empty-","-Empty-","-Empty-","-Empty-","-Empty-"],"rear left leg":["Hip","Upper Leg Actuator","Lower Leg Actuator","Foot Actuator","Heat Sink","Heat Sink","-Empty-","-Empty-","-Empty-","-Empty-","-Empty-","-Empty-"],"rear right leg":["Hip","Upper Leg Actuator","Lower Leg Actuator","Foot Actuator","Heat Sink","Heat Sink","-Empty-","-Empty-","-Empty-","-Empty-","-Empty-","-Empty-"],"designation":"Xanthos XNT-3O","validMTF":true}